JsonNetworkStream-1.0.dist-info/DESCRIPTION.rst
JsonNetworkStream-1.0.dist-info/METADATA
JsonNetworkStream-1.0.dist-info/RECORD
JsonNetworkStream-1.0.dist-info/WHEEL
JsonNetworkStream-1.0.dist-info/metadata.json
JsonNetworkStream-1.0.dist-info/top_level.txt
client/__init__.py
client/my_client.py
server/__init__.py
server/my_server.py
