Metadata-Version: 2.0
Name: JsonNetworkStream
Version: 1.0
Summary: library for data streaming over the network .Can be used for sending data over network ,following a Json Protocol for data transfer.
Home-page: UNKNOWN
Author: Sumit Rana
Author-email: rana.sumit93@gmail.com
License: General
Platform: UNKNOWN
